arcane/numbers.py
arcane_numbers-0.1.0.dist-info/WHEEL
arcane_numbers-0.1.0.dist-info/METADATA
arcane_numbers-0.1.0.dist-info/RECORD
